markdown_jinja.py
setup.cfg
setup.py
markdown_jinja.egg-info/PKG-INFO
markdown_jinja.egg-info/SOURCES.txt
markdown_jinja.egg-info/dependency_links.txt
markdown_jinja.egg-info/requires.txt
markdown_jinja.egg-info/top_level.txt